{
  "chunk_id": "CA2013_S277_4",
  "type": "child",
  "text": "(4) Within three weeks from the date of passing of winding up order, the Company Liquidator shall\nmake an application to the Tribunal for constitution of a winding up committee to assist and monitor the\nprogress of liquidation proceedings by the Company Liquidator in carrying out the function as provided in\nsub-section (5) and such winding up committee shall comprise of the following persons, namely:—\n(i) Official Liquidator attached to the Tribunal;\n(ii) nominee of secured creditors; and\n172\n\n--- PAGE 173 ---\n(iii) a professional nominated by the Tribunal.",
  "act": "CA2013",
  "chapter": null,
  "section_number": "277",
  "section_title": null,
  "parent_id": "CA2013_S277",
  "children_ids": [],
  "tokens": 117,
  "sentence_window": "(2) On receipt of the copy of order of appointment of provisional liquidator or winding up order, the\nRegistrar shall make an endorsement to that effect in his records relating to the company and notify in the\nOfficial Gazette that such an order has been made and in the case of a listed company, the Registrar shall\nintimate about such appointment or order, as the case may be, to the stock exchange or exchanges where\nthe securities of the company are listed. (3) The winding up order shall be deemed to be a notice of discharge to the officers, employees and\nworkmen of the company, except when the business of the company is continued. (4) Within three weeks from the date of passing of winding up order, the Company Liquidator shall\nmake an application to the Tribunal for constitution of a winding up committee to assist and monitor the\nprogress of liquidation proceedings by the Company Liquidator in carrying out the function as provided in\nsub-section (5) and such winding up committee shall comprise of the following persons, namely:—\n(i) Official Liquidator attached to the Tribunal;\n(ii) nominee of secured creditors; and\n172\n\n--- PAGE 173 ---\n(iii) a professional nominated by the Tribunal. (5) The Company Liquidator shall be the convener of the meetings of the winding up committee which\nshall assist and monitor the liquidation proceedings in following areas of liquidation functions, namely:—\n(i) taking over assets;\n(ii) examination of the statement of affairs;\n(iii) recovery of property, cash or any other assets of the company including benefits derived\ntherefrom;\n(iv) review of audit reports and accounts of the company;\n(v) sale of assets;\n(vi) finalisation of list of creditors and contributories;\n(vii) compromise, abandonment and settlement of claims;\n(viii) payment of dividends, if any; and\n(ix) any other function, as the Tribunal may direct from time to time. (6) The Company Liquidator shall place before the Tribunal a report along with minutes of the meetings\nof the committee on monthly basis duly signed by the members present in the meeting for consideration till\nthe final report for dissolution of the company is submitted before the Tribunal.",
  "cross_references": [
    "sub-section (5)"
  ],
  "source_file": "Companies_Act_2013.pdf",
  "source_page": null,
  "name": null,
  "year": null,
  "ministry": null,
  "source_url": null,
  "total_sections": null,
  "structured": null
}