{
  "chunk_id": "CA2013_S378T_2",
  "type": "child",
  "text": "(2) Without prejudice to the provisions contained in sub-section (1), the Producer Company shall have\nthe right to recover from its director—\n(a) where such director has made any profit as a result of the contravention specified in\nsub-section (1), an amount equal to the profit so made;\n(b) where the Producer Company incurred a loss or damage as a result of the contravention specified\nin sub-section (1), an amount equal to that loss or damage.",
  "act": "CA2013",
  "chapter": null,
  "section_number": "378T",
  "section_title": null,
  "parent_id": "CA2013_S378T",
  "children_ids": [],
  "tokens": 100,
  "sentence_window": "378T. Liability of directors.— (1) When the directors vote for a resolution, or approve by any other\nmeans, anything done in contravention of the provisions of this Act or any other law for the time being in\nforce or articles, they shall be jointly and severally liable to make good any loss or damage suffered by the\nProducer Company. (2) Without prejudice to the provisions contained in sub-section (1), the Producer Company shall have\nthe right to recover from its director—\n(a) where such director has made any profit as a result of the contravention specified in\nsub-section (1), an amount equal to the profit so made;\n(b) where the Producer Company incurred a loss or damage as a result of the contravention specified\nin sub-section (1), an amount equal to that loss or damage. (3) The liability imposed under this section shall be in addition to and not in derogation of a liability\nimposed on a director under this Act or any other law for the time being in force. 378U.",
  "cross_references": [
    "sub-section (1)"
  ],
  "source_file": "Companies_Act_2013.pdf",
  "source_page": null,
  "name": null,
  "year": null,
  "ministry": null,
  "source_url": null,
  "total_sections": null,
  "structured": null
}