{
  "chunk_id": "CA2013_S442_5",
  "type": "child",
  "text": "(5) The Mediation and Conciliation Panel shall follow such procedure as may be prescribed and dispose\nof the matter referred to it within a period of three months from the date of such reference and forward its\nrecommendations to the Central Government or the Tribunal or the Appellate Tribunal, as the case may be.",
  "act": "CA2013",
  "chapter": null,
  "section_number": "442",
  "section_title": null,
  "parent_id": "CA2013_S442",
  "children_ids": [],
  "tokens": 65,
  "sentence_window": "(3) The Central Government or the Tribunal or the Appellate Tribunal before which any proceeding is\npending may, suo motu, refer any matter pertaining to such proceeding to such number of experts from the\nMediation and Conciliation Panel as the Central Government or the Tribunal or the Appellate Tribunal, as\nthe case may be, deems fit. (4) The fee and other terms and conditions of experts of the Mediation and Conciliation Panel shall be\nsuch as may be prescribed. (5) The Mediation and Conciliation Panel shall follow such procedure as may be prescribed and dispose\nof the matter referred to it within a period of three months from the date of such reference and forward its\nrecommendations to the Central Government or the Tribunal or the Appellate Tribunal, as the case may be. (6) Any party aggreived by the recommendation of the Mediation and Conciliation Panel may file\nobjections to the Central Government or the Tribunal or the Appellate Tribunal, as the case may be. 443.",
  "cross_references": [],
  "source_file": "Companies_Act_2013.pdf",
  "source_page": null,
  "name": null,
  "year": null,
  "ministry": null,
  "source_url": null,
  "total_sections": null,
  "structured": null
}