{
  "chunk_id": "CA2013_S15_2",
  "type": "child",
  "text": "(2) If a company makes any default in complying with the provisions of sub-section (1), the company\nand every officer who is in default shall be liable to a penalty of one thousand rupees for every copy of the\nmemorandum or articles issued without such alteration.",
  "act": "CA2013",
  "chapter": null,
  "section_number": "15",
  "section_title": null,
  "parent_id": "CA2013_S15",
  "children_ids": [],
  "tokens": 57,
  "sentence_window": "15. Alteration of memorandum or articles to be noted in every copy.—(1) Every alteration made in\nthe memorandum or articles of a company shall be noted in every copy of the memorandum or articles, as\nthe case may be. (2) If a company makes any default in complying with the provisions of sub-section (1), the company\nand every officer who is in default shall be liable to a penalty of one thousand rupees for every copy of the\nmemorandum or articles issued without such alteration. 16. Rectification of name of company.—(1) If, through inadvertence or otherwise, a company on its\nfirst registration or on its registration by a new name, is registered by a name which,—\n(a) in the opinion of the Central Government, is identical with or too nearly resembles the name by\nwhich a company in existence had been previously registered, whether under this Act or any previous\ncompany law, it may direct the company to change its name and the company shall change its name or\nnew name, as the case may be, within a period of three months from the issue of such direction, after\nadopting an ordinary resolution for the purpose;\n(b) on an application by a registered proprietor of a trade mark that the name is identical with or\ntoo nearly resembles to a registered trade mark of such proprietor under the Trade Marks Act, 1999 (47\nof 1999), made to the Central Government within three years of incorporation or registration or change\nof name of the company, whether under this Act or any previous company law, in the opinion of the\nCentral Government, is identical with or too nearly resembles to an existing trade mark, it may direct\nthe company to change its name and the company shall change its name or new name, as the case may\nbe, within a 3[period of three months] from the issue of such direction, after adopting an ordinary\nresolution for the purpose.",
  "cross_references": [
    "sub-section (1)"
  ],
  "source_file": "Companies_Act_2013.pdf",
  "source_page": null,
  "name": null,
  "year": null,
  "ministry": null,
  "source_url": null,
  "total_sections": null,
  "structured": null
}