{
  "chunk_id": "CA2013_S291_2",
  "type": "child",
  "text": "(2) Any person appointed under this section shall disclose forthwith to the Tribunal in the prescribed\nform any conflict of interest or lack of independence in respect of his appointment.",
  "act": "CA2013",
  "chapter": null,
  "section_number": "291",
  "section_title": null,
  "parent_id": "CA2013_S291",
  "children_ids": [],
  "tokens": 35,
  "sentence_window": "291. Provision for professional assistance to Company Liquidator.—(1) The Company Liquidator\nmay, with the sanction of the Tribunal, appoint one or more chartered accountants or company secretaries\n177\n\n--- PAGE 178 ---\nor cost accountants or legal practitioners or such other professionals on such terms and conditions, as may\nbe necessary, to assist him in the performance of his duties and functions under this Act. (2) Any person appointed under this section shall disclose forthwith to the Tribunal in the prescribed\nform any conflict of interest or lack of independence in respect of his appointment. 292. Exercise and control of Company Liquidator’s powers.—(1) Subject to the provisions of this\nAct, the Company Liquidator shall, in the administration of the assets of the company and the distribution\nthereof among its creditors, have regard to any directions which may be given by the resolution of the\ncreditors or contributories at any general meeting or by the advisory committee.",
  "cross_references": [],
  "source_file": "Companies_Act_2013.pdf",
  "source_page": null,
  "name": null,
  "year": null,
  "ministry": null,
  "source_url": null,
  "total_sections": null,
  "structured": null
}