{
  "chunk_id": "CA2013_S56",
  "type": "parent",
  "text": "56. (i) No objection shall be raised to the qualification of any voter except at the meeting or adjourned meeting\nat which the vote objected to is given or tendered, and every vote not disallowed at such meeting shall be valid for all\npurposes.\n(ii) Any such objection made in due time shall be referred to the Chairperson of the meeting, whose decision shall\nbe final and conclusive.\n266\n\n--- PAGE 267 ---\nProxy",
  "act": "CA2013",
  "chapter": null,
  "section_number": "56",
  "section_title": "56. (i) No objection shall be raised to the qualification of any voter except at the meeting or adjourned meeting",
  "parent_id": null,
  "children_ids": [],
  "tokens": 93,
  "sentence_window": null,
  "cross_references": [],
  "source_file": "Companies_Act_2013.pdf",
  "source_page": null,
  "name": null,
  "year": null,
  "ministry": null,
  "source_url": null,
  "total_sections": null,
  "structured": null
}