{
  "chunk_id": "CA2013_S5_16",
  "type": "child",
  "text": "(16) Notwithstanding anything contained in this Act, any investigation or other action taken or initiated\nby Serious Fraud Investigation Office under the provisions of the Companies Act, 1956 (1 of 1956) shall\ncontinue to be proceeded with under that Act as if this Act had not been passed.",
  "act": "CA2013",
  "chapter": null,
  "section_number": "5",
  "section_title": null,
  "parent_id": "CA2013_S5",
  "children_ids": [],
  "tokens": 62,
  "sentence_window": "(14) On receipt of the investigation report, the Central Government may, after examination of the report\n(and after taking such legal advice, as it may think fit), direct the Serious Fraud Investigation Office to\ninitiate prosecution against the company and its officers or employees, who are or have been in employment\nof the company or any other person directly or indirectly connected with the affairs of the company. 1[(14A) Where the report under sub-section (11) or sub-section (12) states that fraud has taken place in\na company and due to such fraud any director, key managerial personnel, other officer of the company or\nany other person or entity, has taken undue advantage or benefit, whether in the form of any asset, property\nor cash or in any other manner, the Central Government may file an application before the Tribunal for\nappropriate orders with regard to disgorgement of such asset, property or cash and also for holding such\ndirector, key managerial personnel, other officer or any other person liable personally without any limitation\nof liability.]\n(15) Notwithstanding anything contained in this Act or in any other law for the time being in force, the\ninvestigation report filed with the Special Court for framing of charges shall be deemed to be a report filed\nby a police officer under section 173 of the Code of Criminal Procedure, 1973 (2 of 1974). (16) Notwithstanding anything contained in this Act, any investigation or other action taken or initiated\nby Serious Fraud Investigation Office under the provisions of the Companies Act, 1956 (1 of 1956) shall\ncontinue to be proceeded with under that Act as if this Act had not been passed. (17) (a) In case Serious Fraud Investigation Office has been investigating any offence under this Act,\nany other investigating agency, State Government, police authority, income-tax authorities having any\ninformation or documents in respect of such offence shall provide all such information or documents\navailable with it to the Serious Fraud Investigation Office;\n(b) The Serious Fraud Investigation Office shall share any information or documents available with it,\nwith any investigating agency, State Government, police authority or income-tax authorities, which may be\nrelevant or useful for such investigating agency, State Government, police authority or income-tax\nauthorities in respect of any offence or matter being investigated or examined by it under any other law. 213.",
  "cross_references": [],
  "source_file": "Companies_Act_2013.pdf",
  "source_page": null,
  "name": null,
  "year": null,
  "ministry": null,
  "source_url": null,
  "total_sections": null,
  "structured": null
}