{
  "chunk_id": "CA2013_S415",
  "type": "parent",
  "text": "415. Acting President and Chairperson of Tribunal or Appellate Tribunal.—(1) In the event of the\noccurrence of any vacancy in the office of the President or the Chairperson by reason of his death,\nresignation or otherwise, the senior-most Member shall act as the President or the Chairperson, as the case\nmay be, until the date on which a new President or Chairperson appointed in accordance with the provisions\nof this Act to fill such vacancy enters upon his office.\n(2) When the President or the Chairperson is unable to discharge his functions owing to absence, illness\nor any other cause, the senior-most Member shall discharge the functions of the President or the\nChairperson, as the case may be, until the date on which the President or the Chairperson resumes his duties.",
  "act": "CA2013",
  "chapter": null,
  "section_number": "415",
  "section_title": "415. Acting President and Chairperson of Tribunal or Appellate Tribunal.—(1) In the event of the",
  "parent_id": null,
  "children_ids": [
    "CA2013_S415_2"
  ],
  "tokens": 167,
  "sentence_window": null,
  "cross_references": [],
  "source_file": "Companies_Act_2013.pdf",
  "source_page": null,
  "name": null,
  "year": null,
  "ministry": null,
  "source_url": null,
  "total_sections": null,
  "structured": null
}