{
  "chunk_id": "CA2013_S56_5",
  "type": "child",
  "text": "(5) The transfer of any security or other interest of a deceased person in a company made by his legal\nrepresentative shall, even if the legal representative is not a holder thereof, be valid as if he had been the\nholder at the time of the execution of the instrument of transfer.\n51\n\n--- PAGE 52 ---\n1[(6) Where any default is made in complying with the provisions of sub-sections (1) to (5), the\ncompany and every officer of the company who is in default shall be liable to a penalty of fifty thousand\nrupees.]",
  "act": "CA2013",
  "chapter": null,
  "section_number": "56",
  "section_title": null,
  "parent_id": "CA2013_S56",
  "children_ids": [],
  "tokens": 118,
  "sentence_window": "(3) Where an application is made by the transferor alone and relates to partly paid shares, the transfer\nshall not be registered, unless the company gives the notice of the application, in such manner as may be\nprescribed, to the transferee and the transferee gives no objection to the transfer within two weeks from the\nreceipt of notice. (4) Every company shall, unless prohibited by any provision of law or any order of Court, Tribunal or\nother authority, deliver the certificates of all securities allotted, transferred or transmitted—\n(a) within a period of two months from the date of incorporation, in the case of subscribers to the\nmemorandum;\n(b) within a period of two months from the date of allotment, in the case of any allotment of any of\nits shares;\n(c) within a period of one month from the date of receipt by the company of the instrument of\ntransfer under sub-section (1) or, as the case may be, of the intimation of transmission under sub-\nsection (2), in the case of a transfer or transmission of securities;\n(d) within a period of six months from the date of allotment in the case of any allotment of\ndebenture:\nProvided that where the securities are dealt with in a depository, the company shall intimate the details\nof allotment of securities to depository immediately on allotment of such securities. (5) The transfer of any security or other interest of a deceased person in a company made by his legal\nrepresentative shall, even if the legal representative is not a holder thereof, be valid as if he had been the\nholder at the time of the execution of the instrument of transfer.\n51\n\n--- PAGE 52 ---\n1[(6) Where any default is made in complying with the provisions of sub-sections (1) to (5), the\ncompany and every officer of the company who is in default shall be liable to a penalty of fifty thousand\nrupees.] (7) Without prejudice to any liability under the Depositories Act, 1996 (22 of 1996), where any\ndepository or depository participant, with an intention to defraud a person, has transferred shares, it shall\nbe liable under section 447. 57.",
  "cross_references": [],
  "source_file": "Companies_Act_2013.pdf",
  "source_page": null,
  "name": null,
  "year": null,
  "ministry": null,
  "source_url": null,
  "total_sections": null,
  "structured": null
}