{
  "chunk_id": "CA2013_S300_4",
  "type": "child",
  "text": "(4) A person ordered to be examined under this section—\n(a) shall, before his examination, be furnished at his own cost with a copy of the report of the\nCompany Liquidator; and\n(b) may at his own cost employ chartered accountants or company secretaries or cost accountants\nor legal practitioners entitled to appear before the Tribunal under section 432, who shall be at liberty to\nput to him such questions as the Tribunal may consider just for the purpose of enabling him to explain\nor qualify any answers given by him.",
  "act": "CA2013",
  "chapter": null,
  "section_number": "300",
  "section_title": null,
  "parent_id": "CA2013_S300",
  "children_ids": [],
  "tokens": 113,
  "sentence_window": "(2) The Company Liquidator shall take part in the examination, and for that purpose he or it may, if\nspecially authorised by the Tribunal in that behalf, employ such legal assistance as may be sanctioned by\nthe Tribunal. (3) The person shall be examined on oath and shall answer all such questions as the Tribunal may put,\nor allow to be put, to him. (4) A person ordered to be examined under this section—\n(a) shall, before his examination, be furnished at his own cost with a copy of the report of the\nCompany Liquidator; and\n(b) may at his own cost employ chartered accountants or company secretaries or cost accountants\nor legal practitioners entitled to appear before the Tribunal under section 432, who shall be at liberty to\nput to him such questions as the Tribunal may consider just for the purpose of enabling him to explain\nor qualify any answers given by him. (5) If any such person applies to the Tribunal to be exculpated from any charges made or suggested\nagainst him, it shall be the duty of the Company Liquidator to appear on the hearing of such application\nand call the attention of the Tribunal to any matters which appear to the Company Liquidator to be relevant. (6) If the Tribunal, after considering any evidence given or hearing witnesses called by the Company\nLiquidator, allows the application made under sub-section (5), the Tribunal may order payment to the\napplicant of such costs as it may think fit.",
  "cross_references": [
    "section 432"
  ],
  "source_file": "Companies_Act_2013.pdf",
  "source_page": null,
  "name": null,
  "year": null,
  "ministry": null,
  "source_url": null,
  "total_sections": null,
  "structured": null
}