{
  "chunk_id": "CA2013_S467_2",
  "type": "child",
  "text": "(2) Any alteration notified under sub-section (1) shall have effect as if enacted in this Act and shall\ncome into force on the date of the notification, unless the notification otherwise directs:\nProvided that no such alteration in Table F of Schedule I shall apply to any company registered before\nthe date of such alteration.",
  "act": "CA2013",
  "chapter": null,
  "section_number": "467",
  "section_title": null,
  "parent_id": "CA2013_S467",
  "children_ids": [],
  "tokens": 66,
  "sentence_window": "467. Power of Central Government to amend Schedules.—(1) Subject to the provisions of this\nsection, the Central Government may, by notification, alter any of the regulations, rules, Tables, forms and\nother provisions contained in any of the Schedules to this Act. (2) Any alteration notified under sub-section (1) shall have effect as if enacted in this Act and shall\ncome into force on the date of the notification, unless the notification otherwise directs:\nProvided that no such alteration in Table F of Schedule I shall apply to any company registered before\nthe date of such alteration. (3) Every alteration made by the Central Government under sub-section (1) shall be laid as soon as may\nbe after it is made before each House of Parliament while it is in session for a total period of thirty days\nwhich may be comprised in one session or in two or more successive sessions, and if, before the expiry of\nthe session immediately following the session or the successive sessions aforesaid, both Houses agree in\nmaking any modification in the alteration, or both Houses agree that the alteration should not be made, the\nalteration shall thereafter have effect only in such modified form or be of no effect, as the case may be; so,\nhowever, that any such modification or annulment shall be without prejudice to the validity of anything\npreviously done in pursuance of that alteration. 468.",
  "cross_references": [
    "Schedule I",
    "sub-section (1)"
  ],
  "source_file": "Companies_Act_2013.pdf",
  "source_page": null,
  "name": null,
  "year": null,
  "ministry": null,
  "source_url": null,
  "total_sections": null,
  "structured": null
}