{
  "chunk_id": "CSCR2014_S9_6",
  "type": "child",
  "text": "(6) A company may redeem its preference shares only on the terms on which they were issued or as\nvaried after due approval of preference shareholders under section 48 of the Act and the preference shares\nmay be redeemed:—\n(a) at a fixed time or on the happening of a particular event;\n(b) any time at the company's option; or\n(c) any time at the shareholder's option.",
  "act": "CSCR2014",
  "chapter": null,
  "section_number": "9",
  "section_title": null,
  "parent_id": "CSCR2014_S9",
  "children_ids": [],
  "tokens": 85,
  "sentence_window": "(4) Where a company issues preference shares, the Register of Members maintained under section 88\nshall contain the particulars in respect of such preference shareholder(s). (5) A company intending to list its preference shares on a recognized stock exchange shall issue such\nshares in accordance with the regulations made by the Securities and Exchange Board of India in this\nbehalf. (6) A company may redeem its preference shares only on the terms on which they were issued or as\nvaried after due approval of preference shareholders under section 48 of the Act and the preference shares\nmay be redeemed:—\n(a) at a fixed time or on the happening of a particular event;\n(b) any time at the company's option; or\n(c) any time at the shareholder's option. 10. Issue and redemption of preference shares by company in infrastructural projects.",
  "cross_references": [
    "section 48"
  ],
  "source_file": "Companies_Share_Capital_Rules_2014.pdf",
  "source_page": null,
  "name": null,
  "year": null,
  "ministry": null,
  "source_url": null,
  "total_sections": null,
  "structured": null
}