{
  "chunk_id": "SEBI_AIF2012_S19M_12",
  "type": "child",
  "text": "(12) All Alternative Investment Funds shall inform the Board in case of any 121[***] material\nchange from the information provided by the Alternative Investment Fund at the time of\napplication for registration.",
  "act": "SEBI_AIF2012",
  "chapter": null,
  "section_number": "19M",
  "section_title": null,
  "parent_id": "SEBI_AIF2012_S19M",
  "children_ids": [],
  "tokens": 41,
  "sentence_window": "(11) The Sponsor or Manager of the Alternative Investment Fund shall appoint a custodian\nregistered with the Board for safekeeping of the securities if the corpus of the Alternative\nInvestment Fund is more than five hundred crore rupees:\nProvided that the Sponsor or Manager of a Category III Alternative Investment Fund shall appoint\nsuch a custodian, irrespective of the size of the corpus of the Alternative Investment Fund:\nProvided further that the custodian appointed by Category III Alternative Investment Fund shall\nkeep the custody of the securities and goods received in delivery against the physical settlement\nof commodity derivatives. 120[ Provided further that the Sponsor or Manager of the Category I and Category II Alternative\nInvestment Fund transacting in credit default swaps shall appoint a custodian registered with the\nBoard and comply with such terms and conditions as may be specified by the Board.] (12) All Alternative Investment Funds shall inform the Board in case of any 121[***] material\nchange from the information provided by the Alternative Investment Fund at the time of\napplication for registration. (13) In case of 122[change of Sponsor or Manager, or] change in control of the Alternative\nInvestment Fund, Sponsor or Manager, prior approval from the Board shall be taken by the\n120 Inserted by the Securities and Exchange Board of India (Alternative Investment Funds) (Amendment) Regulations,\n2023, w.e.f 09-01-2023. 121 Omitted by the Securities and Exchange Board of India (Alternative Investment Funds) (Fourth Amendment)\nRegulations, 2022, w.e.f.",
  "cross_references": [],
  "source_file": "SEBI_AIF_Regulations_2012.pdf",
  "source_page": null,
  "name": null,
  "year": null,
  "ministry": null,
  "source_url": null,
  "total_sections": null,
  "structured": null
}