{
  "chunk_id": "SEBI_AIF2012_S16_4",
  "type": "child",
  "text": "(4) The following conditions shall apply to social 77[impact] funds in addition to the conditions\nlaid down in sub-regulation (1):-\n(a) 78[at least seventy-five percent of the investable funds shall be invested in unlisted\nsecurities or partnership interest of social ventures or in units of social ventures or in\nsecurities of social enterprises:\nProvided that an existing social impact fund may invest the remaining investable funds\nin securities of not for profit organizations registered or listed on a social stock\nexchange with the prior consent of atleast 75% of the investors by value of their\ninvestment;]\n(b) such funds may accept grants, provided that such utilization of such grants shall be\nrestricted to clause (a) 79[:]\n80[Provided that the amount of grant that may be accepted by the fund from any person\nshall not be less than 81[ten lakh rupees]:\n82[Provided further that the minimum amount of grant shall not apply to accredited\ninvestors:]\nProvided further that no profits or gains shall accrue to the provider of such grants.]\n77 Substituted for the word “venture” by the Securities and Exchange Board of India (Alternative Investment Funds)\n(Third Amendment) Regulations, 2022 w.e.f 25.07.2022.\n78 Substituted by the Securities and Exchange Board of India (Alternative Investment Funds) (Third Amendment)\nRegulations, 2022 w.e.f 25.07.2022. Prior to the substitution, clause (a) of sub-regulation (4) of regulation 16 read as\nunder:\n“atleast seventy five percent of the *[investable funds] shall be invested in unlisted securities or partnership interest\nof social ventures.”\n* Substituted for “corpus” by the Securities and Exchange Board of India (Alternative Investment Funds)\n(Amendment) Regulations, 2013, w.e.f. 16-9-2013.\n79 Substituted by the Securities and Exchange Board of India (Alternative Investment Fund) (Amendment)\nRegulations, 2013, w.e..f 16-09-2013 for the symbol “.”\n80 Inserted by the Securities and Exchange Board of India (Alternative Investment Fund) (Amendment) Regulations,\n2013, w.e..f 16-09-2013\n81 Substituted for the words “twenty five lakh rupees” by the Securities and Exchange Board of India (Alternative\nInvestment Funds) (Third Amendment) Regulations, 2022 w.e.f 25.07.2022.\n82 Inserted by the Securities and Exchange Board of India (Alternative Investment Funds) (Fourth Amendment)\nRegulations, 2018, w.e.f. 13-08-2021.\n\n--- PAGE 30 ---\n83[(ba) Notwithstanding the provisions of clauses (a) and (b), a social impact fund or\nschemes of a social impact fund launched exclusively for a not for profit organization\nregistered or listed on a social stock exchange, shall be permitted to deploy or invest\nhundred percent of the investable funds in the securities of not for profit organizations\nregistered or listed on a social stock exchange.]\n(c) such funds may give grants to social ventures 84[or social enterprises], provided that\nappropriate disclosure is made in the placement memorandum.\n(d) 85[***]",
  "act": "SEBI_AIF2012",
  "chapter": null,
  "section_number": "16",
  "section_title": null,
  "parent_id": "SEBI_AIF2012_S16",
  "children_ids": [],
  "tokens": 699,
  "sentence_window": "13-08-2021. Prior to the substitution, it read as-\n“(c) such funds shall be exempt from regulation 3 and 3A of Securities and Exchange Board of India (Prohibition of\nInsider Trading) Regulations, 1992 in respect of investment in companies listed on SME Exchange or SME segment\nof an exchange pursuant to due diligence of such companies subject to the following conditions:\n(i) the fund shall disclose any acquisition or dealing in securities pursuant to such due-diligence, within two working\ndays of such acquisition or dealing, to the stock exchanges where the investee company is listed;\n(ii) such investment shall be locked in for a period of one year from the date of investment.”\n\n--- PAGE 29 ---\n(i) the fund shall disclose any trading in securities pursuant to such due-diligence,\nwithin two trading days of such trading, to the stock exchanges where the\ninvestee company is listed;\n(ii) such investment shall be locked in for a period of one year from the date of\ninvestment.] (4) The following conditions shall apply to social 77[impact] funds in addition to the conditions\nlaid down in sub-regulation (1):-\n(a) 78[at least seventy-five percent of the investable funds shall be invested in unlisted\nsecurities or partnership interest of social ventures or in units of social ventures or in\nsecurities of social enterprises:\nProvided that an existing social impact fund may invest the remaining investable funds\nin securities of not for profit organizations registered or listed on a social stock\nexchange with the prior consent of atleast 75% of the investors by value of their\ninvestment;]\n(b) such funds may accept grants, provided that such utilization of such grants shall be\nrestricted to clause (a) 79[:]\n80[Provided that the amount of grant that may be accepted by the fund from any person\nshall not be less than 81[ten lakh rupees]:\n82[Provided further that the minimum amount of grant shall not apply to accredited\ninvestors:]\nProvided further that no profits or gains shall accrue to the provider of such grants.]\n77 Substituted for the word “venture” by the Securities and Exchange Board of India (Alternative Investment Funds)\n(Third Amendment) Regulations, 2022 w.e.f 25.07.2022.\n78 Substituted by the Securities and Exchange Board of India (Alternative Investment Funds) (Third Amendment)\nRegulations, 2022 w.e.f 25.07.2022. Prior to the substitution, clause (a) of sub-regulation (4) of regulation 16 read as\nunder:\n“atleast seventy five percent of the *[investable funds] shall be invested in unlisted securities or partnership interest\nof social ventures.”\n* Substituted for “corpus” by the Securities and Exchange Board of India (Alternative Investment Funds)\n(Amendment) Regulations, 2013, w.e.f. 16-9-2013.\n79 Substituted by the Securities and Exchange Board of India (Alternative Investment Fund) (Amendment)\nRegulations, 2013, w.e..f 16-09-2013 for the symbol “.”\n80 Inserted by the Securities and Exchange Board of India (Alternative Investment Fund) (Amendment) Regulations,\n2013, w.e..f 16-09-2013\n81 Substituted for the words “twenty five lakh rupees” by the Securities and Exchange Board of India (Alternative\nInvestment Funds) (Third Amendment) Regulations, 2022 w.e.f 25.07.2022.\n82 Inserted by the Securities and Exchange Board of India (Alternative Investment Funds) (Fourth Amendment)\nRegulations, 2018, w.e.f. 13-08-2021.\n\n--- PAGE 30 ---\n83[(ba) Notwithstanding the provisions of clauses (a) and (b), a social impact fund or\nschemes of a social impact fund launched exclusively for a not for profit organization\nregistered or listed on a social stock exchange, shall be permitted to deploy or invest\nhundred percent of the investable funds in the securities of not for profit organizations\nregistered or listed on a social stock exchange.]\n(c) such funds may give grants to social ventures 84[or social enterprises], provided that\nappropriate disclosure is made in the placement memorandum.\n(d) 85[***] (5) The following conditions shall apply to Infrastructure Funds in addition to conditions laid\ndown in sub-regulation (1):-\n(a) atleast seventy five percent of the 86[investable funds] shall be invested in unlisted\nsecurities or units or partnership interest of venture capital undertaking or investee\ncompanies or special purpose vehicles, which are engaged in or formed for the purpose\nof operating, developing or holding infrastructure projects 87[or in units of Category\nII Alternative Investment Funds which invest primarily in such venture capital\nundertakings or investee companies or special purpose vehicles];\n(b) notwithstanding clause (a) of sub-regulation (5), such funds may also invest in listed\nsecuritized debt instruments or listed debt securities of investee companies or special\npurpose vehicles, which are engaged in or formed for the purpose of operating,\ndeveloping or holding infrastructure projects. Conditions for Category II Alternative Investment Funds.",
  "cross_references": [],
  "source_file": "SEBI_AIF_Regulations_2012.pdf",
  "source_page": null,
  "name": null,
  "year": null,
  "ministry": null,
  "source_url": null,
  "total_sections": null,
  "structured": null
}