{
  "chunk_id": "SEBI_ICDR2018_S5_19",
  "type": "child",
  "text": "(19) Interest on refund of excess bid amount, in case of anchor investors.",
  "act": "SEBI_ICDR2018",
  "chapter": null,
  "section_number": "5",
  "section_title": null,
  "parent_id": "SEBI_ICDR2018_S5",
  "children_ids": [],
  "tokens": 17,
  "sentence_window": "(17) Disposal of applications. (18) Provisions of the Companies Act, 2013, as applicable, relating to punishment for\nfictitious applications, including to any person who:\n(a) makes or abets making of an application in a fictitious name to a\ncompany for acquiring, or subscribing for, its securities, or\n162\n\n--- PAGE 163 ---\n(b) makes or abets making of multiple applications to a company in\ndifferent names or in different combinations of his/her name or surname\nfor acquiring or subscribing for its securities, shall be punishable with\nfine and/or imprisonment for such amount and/or term as may be\nprescribed under section 447 of the Companies Act 2013. (19) Interest on refund of excess bid amount, in case of anchor investors. (20) Names of entities responsible for finalising the basis of allotment in a fair and\nproper manner. (21) Procedure and time of schedule for allotment and issue of certificates (for rights\nissues)/demat credit.",
  "cross_references": [],
  "source_file": "SEBI_ICDR_Regulations_2018.pdf",
  "source_page": null,
  "name": null,
  "year": null,
  "ministry": null,
  "source_url": null,
  "total_sections": null,
  "structured": null
}