{
  "chunk_id": "SEBI_ICDR2018_S237",
  "type": "parent",
  "text": "237. (1) For the computation of minimum promoters’ contribution, the following specified\nsecurities shall not be eligible:\na) specified securities acquired during the preceding three years, if they are:\n(i) acquired for consideration other than cash and revaluation of assets or capitalisation of\nintangible assets is involved in such transaction; or\n(ii) resulting from a bonus issue by utilisation of revaluation reserves or unrealised profits\nof the issuer or from bonus issue against equity shares which are ineligible for\nminimum promoters’ contribution;\nb) specified securities acquired by the promoters and alternative investment funds or foreign\nventure capital investors or scheduled commercial banks or public financial institutions or\ninsurance companies registered with Insurance Regulatory and Development Authority of\nIndia, during the preceding one year at a price lower than the price at which specified\nsecurities are being offered to the public in the initial public offer:\nProvided that nothing contained in this clause shall apply:\n(i) if the promoters and alternative investment funds as applicable, pay to the issuer the\ndifference between the price at which the specified securities are offered in the initial\npublic offer and the price at which the specified securities had been acquired;\n(ii) if such specified securities are acquired in terms of the scheme under 391 to 394 of the\nCompanies Act, 1956 or sections 230 to 234 of the Companies Act, 2013, as approved\nby a High Court or a tribunal, as applicable, by the promoters in lieu of business and\n88\n\n--- PAGE 89 ---\ninvested capital that had been in existence for a period of more than one year prior to\nsuch approval;\n(iii) to an initial public offer by a government company, statutory authority or corporation or\nany special purpose vehicle set up by any of them, which is engaged in the\ninfrastructure sector;\nc) specified securities allotted to the promoters and alternative investment funds during the\npreceding one year at a price less than the issue price, against funds brought in by them\nduring that period, in case of an issuer formed by conversion of one or more partnership\nfirms or limited liability partnerships, where the partners of the erstwhile partnership firms\nor limited liability partnerships are the promoters of the issuer and there is no change in the\nmanagement:\nProvided that specified securities, allotted to the promoters against the capital existing in\nsuch firms for a period of more than one year on a continuous basis, shall be eligible;\nd) specified securities pledged with any creditor.\n(2) Specified securities referred to in clauses (a) and (c) of sub-regulation (1) shall be eligible for\nthe computation of promoters’ contribution, if such securities are acquired pursuant to a scheme\nwhich has been approved under the Companies Act, 2013 or any previous company law.\nPART IV: LOCK-IN AND RESTRICTIONS ON TRANSFERRABILITY\nLock-in of specified securities held by the promoters",
  "act": "SEBI_ICDR2018",
  "chapter": null,
  "section_number": "237",
  "section_title": "237. (1) For the computation of minimum promoters’ contribution, the following specified",
  "parent_id": null,
  "children_ids": [
    "SEBI_ICDR2018_S237_2"
  ],
  "tokens": 595,
  "sentence_window": null,
  "cross_references": [],
  "source_file": "SEBI_ICDR_Regulations_2018.pdf",
  "source_page": null,
  "name": null,
  "year": null,
  "ministry": null,
  "source_url": null,
  "total_sections": null,
  "structured": null
}