{
  "chunk_id": "SEBI_ICDR2018_S140_3",
  "type": "child",
  "text": "(3) The issue shall be opened after at least three working days from the date of registering the red\nherring prospectus with the Registrar of Companies in case of book built issues and prospectus\nwith the Registrar of Companies in case of fixed price issues.\nMinimum subscription",
  "act": "SEBI_ICDR2018",
  "chapter": null,
  "section_number": "140",
  "section_title": null,
  "parent_id": "SEBI_ICDR2018_S140",
  "children_ids": [],
  "tokens": 55,
  "sentence_window": "(1) Subject to the compliance with the provisions of the Companies Act, 2013, a public issue\nmay be opened within twelve months from the date of issuance of the observations by the Board\nunder sub-regulation (4) of regulation 123; or\nProvided that in case of a fast track issue, the issue shall open within the period specifically\nstipulated under the Companies Act, 2013. (2) In case of shelf prospectus, the first issue may be opened within three months of issuance of\nobservations by the Board. (3) The issue shall be opened after at least three working days from the date of registering the red\nherring prospectus with the Registrar of Companies in case of book built issues and prospectus\nwith the Registrar of Companies in case of fixed price issues.\nMinimum subscription 141. (1) The minimum subscription to be received in the issue shall be at least ninety per cent.",
  "cross_references": [],
  "source_file": "SEBI_ICDR_Regulations_2018.pdf",
  "source_page": null,
  "name": null,
  "year": null,
  "ministry": null,
  "source_url": null,
  "total_sections": null,
  "structured": null
}